Metadata-Version: 2.1
Name: randrandom
Version: 0.0.3
Summary: Improvment on the random libary.
Home-page: 
Author: Abubakr
Author-email: abubakr.sultan14@gmail.com
License: MIT
Keywords: random
Classifier: Development Status :: 5 - Production/Stable
Classifier: Intended Audience :: Education
Classifier: Operating System :: Microsoft :: Windows :: Windows 11
Classifier: License :: OSI Approved :: MIT License
Classifier: Programming Language :: Python :: 3
License-File: LICENSE.txt
